ontonotes5/__init__.py
ontonotes5/utils.py
ontonotes_5_parsing-0.0.5.dist-info/LICENSE
ontonotes_5_parsing-0.0.5.dist-info/METADATA
ontonotes_5_parsing-0.0.5.dist-info/WHEEL
ontonotes_5_parsing-0.0.5.dist-info/entry_points.txt
ontonotes_5_parsing-0.0.5.dist-info/top_level.txt
ontonotes_5_parsing-0.0.5.dist-info/RECORD
