Metadata-Version: 2.1
Name: ontonotes-5-parsing
Version: 0.0.5
Summary: Ontonotes-5-parsing: parser of Ontonotes 5.0 to transform this corpus to a simple JSON format.
Home-page: https://github.com/nsu-ai/ontonotes-5-parsing
Author: Ivan Bondarenko
Author-email: i.bondarenko@g.nsu.ru
License: Apache License Version 2.0
Keywords: ontonotes,ontonotes5,ontonotes-5,ner,nlp,multi-lingual,named-entity-recognizer,named-entity-recognition
Platform: UNKNOWN
Classifier: Development Status :: 3 - Alpha
Classifier: Intended Audience :: Science/Research
Classifier: Intended Audience :: Developers
Classifier: Topic :: Software Development
Classifier: Topic :: Scientific/Engineering
Classifier: Topic :: Scientific/Engineering :: Artificial Intelligence
Classifier: Topic :: Text Processing
Classifier: Topic :: Text Processing :: Linguistic
Classifier: License :: OSI Approved :: Apache Software License
Classifier: Programming Language :: Python :: 3.6
Classifier: Programming Language :: Python :: 3.7
Requires-Dist: tqdm (>=4.43.0)
Requires-Dist: numpy (>=1.18.1)
Requires-Dist: nltk (>=3.5)
Requires-Dist: python-Levenshtein (>=0.12.0)
